threedee/__init__.py
threedee/apps.py
threedee/default_settings.py
threedee/fields.py
threedee/models.py
threedee/paraview_import.py
threedee/permissions.py
threedee/tests.py
threedee/migrations/0001_initial.py
threedee/migrations/0002_add_attachment_roles.py
threedee/migrations/__init__.py
threedee/static/threedee/css/common.css
threedee/static/threedee/css/paraview_webgl_model.css
threedee/static/threedee/css/threedee.css
threedee/static/threedee/js/threedee.js
threedee/static/threedee/js/threedee_worker.js
threedee/templates/threedee/paraview_webgl_model.html
threedee/templates/threedee/tags/support.html
threedee/templatetags/__init__.py
threedee/templatetags/threedee_tags.py
threedee-4.1.1.dist-info/AUTHORS.txt
threedee-4.1.1.dist-info/LICENSE.txt
threedee-4.1.1.dist-info/METADATA
threedee-4.1.1.dist-info/WHEEL
threedee-4.1.1.dist-info/top_level.txt
threedee-4.1.1.dist-info/RECORD
